setfitonnx/__init__.py
setfitonnx/config.py
setfitonnx/model_exporter.py
setfitonnx/onnxexporter.py
setfitonnx/pooler.py
setfitonnx-0.1.0.dist-info/WHEEL
setfitonnx-0.1.0.dist-info/METADATA
setfitonnx-0.1.0.dist-info/RECORD
